{"stat.cakeSlicesEaten":5,"stat.pickup.minecraft.bone":4,"stat.leaveGame":2,"stat.mineBlock.minecraft.cobblestone":5,"stat.pickup.minecraft.stone_pickaxe":3,"stat.pickup.tconstruct.edible":2,"stat.swimOneCm":35252,"stat.pickup.tp.raspberry_berry":1,"stat.useItem.minecraft.stone_slab2":9,"stat.pickup.minecraft.rotten_flesh":7,"stat.craftItem.minecraft.furnace":1,"stat.pickup.thermalfoundation.ore":8,"stat.craftItem.minecraft.stone_axe":1,"stat.craftItem.minecraft.stone_pickaxe":1,"stat.craftItem.minecraft.cooked_beef":9,"stat.pickup.minecraft.cobblestone":47,"stat.flyOneCm":204750,"stat.craftItem.tp.stone_spear":1,"stat.pickup.rustic.slate":1,"stat.mineBlock.minecraft.iron_ore":17,"stat.timeSinceDeath":27333,"stat.craftItem.minecraft.wooden_pickaxe":1,"stat.pickup.minecraft.mutton":16,"stat.useItem.tp.stone_spear":58,"stat.craftItem.minecraft.bed":2,"stat.mineBlock.thermalfoundation.ore":5,"stat.furnaceInteraction":8,"stat.mineBlock.minecraft.coal_ore":45,"stat.drop.openblocks.info_book":2,"stat.pickup.minecraft.beef":9,"stat.pickup.minecraft.furnace":1,"stat.entityKilledBy.Skeleton":3,"stat.sprintOneCm":143815,"stat.craftItem.minecraft.stick":52,"stat.craftItem.minecraft.stone":1,"stat.mineBlock.minecraft.crafting_table":1,"stat.entityKilledBy.tconstruct.blueslime":1,"stat.entityKilledBy.Creeper":1,"stat.deaths":9,"stat.drop":3,"stat.playOneMinute":76917,"stat.killEntity.Sheep":10,"stat.killEntity.Zombie":1,"stat.mineBlock.minecraft.tallgrass":21,"stat.diveOneCm":19206,"stat.pickup.minecraft.cooked_mutton":14,"stat.chestOpened":5,"stat.useItem.minecraft.stone":2,"stat.drop.minecraft.wooden_pickaxe":1,"stat.pickup.minecraft.gravel":13,"stat.pickup.minecraft.arrow":2,"stat.mineBlock.rustic.slate":1,"stat.jump":1153,"stat.pickup.minecraft.coal":86,"stat.fallOneCm":28922,"stat.useItem.minecraft.stone_axe":40,"stat.crouchOneCm":3361,"stat.craftItem.minecraft.iron_ingot":17,"stat.craftItem.minecraft.torch":64,"stat.pickup.minecraft.dirt":45,"stat.craftingTableInteraction":15,"stat.pickup.minecraft.iron_ore":17,"stat.pickup.rustic.tomato_seeds":3,"stat.pickup.minecraft.wooden_pickaxe":4,"stat.pickup.minecraft.leather":12,"stat.damageTaken":3129,"stat.mineBlock.minecraft.furnace":1,"stat.useItem.minecraft.wooden_pickaxe":14,"stat.mineBlock.biomesoplenty.plant_0":56,"stat.pickup.mysticalagriculture.crafting":3,"tombstone:undead_killed":1,"stat.pickup.minecraft.wheat_seeds":5,"stat.entityKilledBy.Zombie":3,"stat.mineBlock.minecraft.gravel":1,"stat.useItem.minecraft.stone_pickaxe":110,"stat.damageDealt":2633,"stat.pickup.harvestcraft.lettuceitem":1,"stat.killEntity.Cow":4,"stat.mineBlock.minecraft.dirt":9,"stat.walkOneCm":143334,"stat.pickup.minecraft.stick":23,"stat.pickup.minecraft.crafting_table":2,"stat.useItem.minecraft.cobblestone":23,"stat.craftItem.minecraft.crafting_table":1,"stat.useItem.minecraft.gravel":5,"stat.pickup.minecraft.log":12,"stat.pickup.openblocks.info_book":2,"stat.useItem.tombstone.gift":1,"stat.pickup.minecraft.stone":8,"stat.pickup.minecraft.sapling":4,"stat.craftItem.minecraft.planks":48,"stat.killEntity.Spider":1,"stat.mobKills":20,"stat.mineBlock.minecraft.log":12,"stat.mineBlock.minecraft.leaves":3,"stat.pickup.tconstruct.slime_boots":2,"stat.pickup.minecraft.red_flower":1,"stat.sneakTime":820,"stat.pickup.minecraft.wool":12,"stat.pickup.rustic.chili_pepper_seeds":4,"stat.mineBlock.minecraft.stone":45}